pybatis/__init__.py
pybatis/admin.py
pybatis/const.py
pybatis/loader.py
pybatis/models.py
pybatis/paging.py
pybatis/render.py
pybatis/tests.py
pybatis/views.py
pybatis/migrations/__init__.py
pybatis/templatetags/__init__.py
pybatis/templatetags/comm_tags.py
pybatis-0.1.2.dist-info/DESCRIPTION.rst
pybatis-0.1.2.dist-info/METADATA
pybatis-0.1.2.dist-info/RECORD
pybatis-0.1.2.dist-info/WHEEL
pybatis-0.1.2.dist-info/metadata.json
pybatis-0.1.2.dist-info/top_level.txt
