Metadata-Version: 2.0
Name: pybatis
Version: 0.1.2
Summary: python for mybatis
Home-page: https://gitee.com/huichengip_chenxf/pybatis
Author: x-debug
Author-email: 512766594@qq.com
License: MIT
Keywords: pybatis
Platform: UNKNOWN
Classifier: Development Status :: 3 - Alpha
Classifier: Framework :: Django
Classifier: Framework :: Django :: 1.10
Classifier: Intended Audience :: Developers
Classifier: License :: OSI Approved :: BSD License
Classifier: Natural Language :: English
Classifier: Programming Language :: Python :: 2
Classifier: Programming Language :: Python :: 2.7
Classifier: Programming Language :: Python :: 3
Classifier: Programming Language :: Python :: 3.4
Classifier: Programming Language :: Python :: 3.5
Requires-Dist: pyjsonmodels
Requires-Dist: pyquery
Requires-Dist: sqlparse
